README.txt
setup.cfg
setup.py
rc/__init__.py
rc.types.egg-info/PKG-INFO
rc.types.egg-info/SOURCES.txt
rc.types.egg-info/dependency_links.txt
rc.types.egg-info/entry_points.txt
rc.types.egg-info/namespace_packages.txt
rc.types.egg-info/not-zip-safe
rc.types.egg-info/paster_plugins.txt
rc.types.egg-info/requires.txt
rc.types.egg-info/top_level.txt
rc/types/__init__.py
rc/types/tests.py