Metadata-Version: 1.0
Name: rc.types
Version: 1.0dev
Summary: RCTypes
Home-page: http://svn.plone.org/svn/plone/plone.example
Author: minev
Author-email: plone-developers@lists.sourceforge.net
License: GPL
Platform: UNKNOWN
Classifier: Framework :: Plone
Classifier: Programming Language :: Python
Classifier: Topic :: Software Development :: Libraries :: Python Modules
